ftp2sftp/__about__.py
ftp2sftp/__init__.py
ftp2sftp/__main__.py
ftp2sftp/ftp2sftp.py
ftp2sftp-0.1.dist-info/METADATA
ftp2sftp-0.1.dist-info/WHEEL
ftp2sftp-0.1.dist-info/licenses/LICENSE
ftp2sftp-0.1.dist-info/RECORD
