Metadata-Version: 2.1
Name: ftp2sftp
Version: 0.1
Summary: A simple FTP to SFTP bridge
Project-URL: Homepage, https://gitlab.com/sparrow.242.de/ftp2sftp
Project-URL: Bug Tracker, https://gitlab.com/sparrow.242.de/ftp2sftp/-/issues
Author-email: Sebastian Meyer <sparrow.242.de@gmail.com>
License-File: LICENSE
Classifier: Development Status :: 3 - Alpha
Classifier: License :: OSI Approved :: GNU General Public License v3 (GPLv3)
Classifier: Operating System :: OS Independent
Classifier: Programming Language :: Python :: 3
Requires-Python: >=3.6
Requires-Dist: paramiko
Requires-Dist: pyftpdlib
